microgp4/__init__.py
microgp4/classes/__init__.py
microgp4/classes/evaluator.py
microgp4/classes/fitness.py
microgp4/classes/frame.py
microgp4/classes/identifiable.py
microgp4/classes/individual.py
microgp4/classes/macro.py
microgp4/classes/monitor.py
microgp4/classes/node_reference.py
microgp4/classes/node_view.py
microgp4/classes/parameter.py
microgp4/classes/paranoid.py
microgp4/classes/population.py
microgp4/classes/readymade_frames.py
microgp4/classes/readymade_macros.py
microgp4/classes/selement.py
microgp4/classes/shared.py
microgp4/classes/value_bag.py
microgp4/ea/__init__.py
microgp4/ea/check.py
microgp4/ea/common.py
microgp4/ea/parametric.py
microgp4/ea/selection.py
microgp4/ea/vanilla.py
microgp4/evaluator_.py
microgp4/fitness/__init__.py
microgp4/fitness/basic.py
microgp4/fitness/reverse.py
microgp4/fitness_.py
microgp4/fitness_log.py
microgp4/framework/__init__.py
microgp4/framework/bnf.py
microgp4/framework/framework.py
microgp4/framework/macro.py
microgp4/framework/parameter.py
microgp4/framework/parameter_structural_global.py
microgp4/framework/parameter_structural_local.py
microgp4/framework/shared.py
microgp4/framework/utilities.py
microgp4/functions.py
microgp4/global_symbols.py
microgp4/operators/__init__.py
microgp4/operators/graph_crossover.py
microgp4/operators/initializers.py
microgp4/operators/mutation.py
microgp4/operators/unroll.py
microgp4/randy/__init__.py
microgp4/randy/randy.py
microgp4/registry.py
microgp4/sys.py
microgp4/tools/dump.py
microgp4/tools/graph.py
microgp4/tools/names.py
microgp4/user_messages/__init__.py
microgp4/user_messages/checks.py
microgp4/user_messages/exception.py
microgp4/user_messages/messaging.py
microgp4-4!2.0a1.dev10.dist-info/LICENSE
microgp4-4!2.0a1.dev10.dist-info/METADATA
microgp4-4!2.0a1.dev10.dist-info/WHEEL
microgp4-4!2.0a1.dev10.dist-info/RECORD
