Metadata-Version: 2.1
Name: microgp4
Version: 4!2.0a1.dev10
Summary: Yet another multi-purpose extensible self-adaptive evolutionary tool
Home-page: https://squillero.github.io/microgp4/
License: Apache-2.0
Keywords: Aritificial Intelligence,Evolutionary Computation,Approximate Optimization,Fuzzer
Author: Giovanni Squillero
Author-email: giovanni.squillero@polito.it
Maintainer: Giovanni Squillero
Maintainer-email: giovanni.squillero@polito.it
Requires-Python: >=3.11,<3.13
Classifier: Development Status :: 5 - Production/Stable
Classifier: Intended Audience :: Information Technology
Classifier: Intended Audience :: Science/Research
Classifier: License :: OSI Approved :: Apache Software License
Classifier: Programming Language :: Python
Classifier: Programming Language :: Python :: 3
Classifier: Programming Language :: Python :: 3.11
Classifier: Topic :: Software Development :: Libraries
Provides-Extra: plot
Requires-Dist: arcade (>=2.6.17,<3.0.0) ; extra == "plot"
Requires-Dist: joblib (>=1.3.1,<2.0.0)
Requires-Dist: matplotlib (>=3.7.1,<4.0.0) ; extra == "plot"
Requires-Dist: networkx (>=3.1,<4.0)
Requires-Dist: numpy (>=1.25.0,<2.0.0)
Requires-Dist: scipy (>=1.11.1,<2.0.0)
Requires-Dist: tqdm (>=4.65.0,<5.0.0)
Project-URL: Repository, https://github.com/squillero/microgp4
